wordsearch/__init__.py
wordsearch-1.0.0.dist-info/LICENSE
wordsearch-1.0.0.dist-info/METADATA
wordsearch-1.0.0.dist-info/WHEEL
wordsearch-1.0.0.dist-info/top_level.txt
wordsearch-1.0.0.dist-info/RECORD
