Metadata-Version: 2.1
Name: wordsearch
Version: 1.0.0
Summary: Package for searching words
Home-page: https://github.com/hdwyx/wordsearch
Author: hdwyx
License: UNKNOWN
Project-URL: Bug Tracker, https://github.com/hdwyx/wordsearch/issues
Platform: UNKNOWN
Classifier: Programming Language :: Python :: 3
Classifier: License :: OSI Approved :: MIT License
Classifier: Operating System :: OS Independent
Requires-Python: >=2.7
